{   "model":"yahma/llama-7b-hf",
    "dataset": "alpaca",
    "lora_rank": 4,
    "learning_rate": 3e-4,
    "lora_dropout": 0.05,
    "weight_decay": 0.00,
    "n_skills": 8,       
    "load_in_8bit":0,  
    "model_family":"gpt",   

    "predict_batch_size": 2,
    "micro_batch_size": 4,
    "train_batch_size": 128,
    "max_input_length": 256,    
    "eval_every":400, 
    "num_train_epochs":3,

    "model_modifier": "vsmear_xr4",
    "modify_modules": ".*attn.*",       
    "modify_layers": "q_proj|v_proj|k_proj",   
    "trainable_param_names": ".*lora_[ab].*|.*selector.*",
    "wandb_project": "test",
    "eval_superni": 1,
    "eval_mmlu": 1

}